diffdev/__init__.py
diffdev/cli.py
diffdev/clipboard.py
diffdev/config.py
diffdev/context.py
diffdev/file_selector.py
diffdev/gitignore.py
diffdev/llm.py
diffdev/patch.py
diffdev/tree_utils.py
diffdev-0.2.6.dist-info/METADATA
diffdev-0.2.6.dist-info/WHEEL
diffdev-0.2.6.dist-info/entry_points.txt
diffdev-0.2.6.dist-info/top_level.txt
diffdev-0.2.6.dist-info/RECORD
