Metadata-Version: 2.2
Name: diffdev
Version: 0.2.6
Summary: A semi-autonomous framework for easily developing repo-wide changes
Author: Mockapapella
License: Apache-2.0
Project-URL: Homepage, https://github.com/Mockapapella/diffdev
Project-URL: Repository, https://github.com/Mockapapella/diffdev.git
Project-URL: Issues, https://github.com/Mockapapella/diffdev/issues
Classifier: Development Status :: 3 - Alpha
Classifier: Environment :: Console
Classifier: Intended Audience :: Developers
Classifier: License :: OSI Approved :: Apache Software License
Classifier: Operating System :: OS Independent
Classifier: Programming Language :: Python :: 3
Classifier: Programming Language :: Python :: 3.11
Classifier: Topic :: Software Development :: Libraries :: Python Modules
Classifier: Topic :: Software Development :: Code Generators
Classifier: Topic :: Software Development :: Version Control :: Git
Requires-Python: >=3.11
Requires-Dist: anthropic>=0.45.0
Requires-Dist: colorama>=0.4.6
Requires-Dist: openai>=1.60.0
Requires-Dist: pathspec>=0.12.1
Requires-Dist: pyperclip>=1.9.0
Provides-Extra: test
Requires-Dist: pytest>=7.0; extra == "test"
